multiiframes2df/README.MD
multiiframes2df/__init__.py
multiiframes2df/requirements.txt
multiiframes2df/thirdparty.json
multiiframes2df-0.10.dist-info/LICENSE.rst
multiiframes2df-0.10.dist-info/METADATA
multiiframes2df-0.10.dist-info/WHEEL
multiiframes2df-0.10.dist-info/top_level.txt
multiiframes2df-0.10.dist-info/RECORD
