Metadata-Version: 2.1
Name: multiiframes2df
Version: 0.10
Summary: scrapes a website (Selenium, SeleniumBase, undetected chromedriver ...) with iframes and returns a DataFrame
Home-page: https://github.com/hansalemaos/multiiframes2df
Author: Johannes Fischer
Author-email: aulasparticularesdealemaosp@gmail.com
License: MIT
Keywords: iframe,scrape
Classifier: Development Status :: 4 - Beta
Classifier: Programming Language :: Python :: 3 :: Only
Classifier: Programming Language :: Python :: 3.10
Classifier: Topic :: Software Development :: Libraries :: Python Modules
Classifier: Topic :: Utilities
License-File: LICENSE.rst
Requires-Dist: lxml2pandas
Requires-Dist: pandas
